{
  "@id": "v0.0.3",
  "@type": "koio:Implementation",
  "identifier": "ark:/99999/fk4474n87d/v0.0.3",
  "title": "3-Year Liver Cancer Risk Score Interpreter Implementation",
  "description": "This object accepts a 3-Year Hepatocellular Cancer risk score as input and generates a recommendation depending on an individual's risk of developing liver cancer.",
  "keywords": "Keywords",
  "hasServiceSpecification": "v0.0.3/service-specification.yaml",
  "hasDeploymentSpecification": "v0.0.3/deployment-specification.yaml",
  "hasPayload": "v0.0.3/interpretLiverCancerRisk.js",
  "@context": [
    "http://kgrid.org/koio/contexts/implementation.jsonld"
  ]
}